vsbasicvsrpp/__init__.py
vsbasicvsrpp/__main__.py
vsbasicvsrpp/activation.py
vsbasicvsrpp/basicvsr.py
vsbasicvsrpp/basicvsr_net.py
vsbasicvsrpp/basicvsr_plusplus_net.py
vsbasicvsrpp/conv.py
vsbasicvsrpp/conv_module.py
vsbasicvsrpp/flow_warp.py
vsbasicvsrpp/hack_registry.py
vsbasicvsrpp/model_utils.py
vsbasicvsrpp/norm.py
vsbasicvsrpp/padding.py
vsbasicvsrpp/sr_backbone.py
vsbasicvsrpp/upsample.py
vsbasicvsrpp/models/basicvsr_plusplus_c128n25_ntire_decompress_track1_20210223-7b2eba02.pth
vsbasicvsrpp/models/basicvsr_plusplus_c128n25_ntire_decompress_track2_20210314-eeae05e6.pth
vsbasicvsrpp/models/basicvsr_plusplus_c128n25_ntire_decompress_track3_20210304-6daf4a40.pth
vsbasicvsrpp/models/basicvsr_plusplus_c128n25_ntire_vsr_20210311-1ff35292.pth
vsbasicvsrpp/models/basicvsr_plusplus_c64n7_8x1_300k_vimeo90k_bd_20210305-ab315ab1.pth
vsbasicvsrpp/models/basicvsr_plusplus_c64n7_8x1_300k_vimeo90k_bi_20210305-4ef437e2.pth
vsbasicvsrpp/models/basicvsr_plusplus_c64n7_8x1_600k_reds4_20210217-db622b2f.pth
vsbasicvsrpp/models/basicvsr_plusplus_deblur_dvd-ecd08b7f.pth
vsbasicvsrpp/models/basicvsr_plusplus_deblur_gopro-3c5bb9b5.pth
vsbasicvsrpp/models/basicvsr_plusplus_denoise-28f6920c.pth
vsbasicvsrpp/models/spynet_20210409-c6c1bd09.pth
vsbasicvsrpp-3.0.0.dist-info/METADATA
vsbasicvsrpp-3.0.0.dist-info/WHEEL
vsbasicvsrpp-3.0.0.dist-info/licenses/LICENSE
vsbasicvsrpp-3.0.0.dist-info/RECORD
