Metadata-Version: 2.4
Name: vsbasicvsrpp
Version: 3.0.0
Summary: BasicVSR++ function for VapourSynth
Project-URL: Homepage, https://github.com/HolyWu/vs-basicvsrpp
Project-URL: Issues, https://github.com/HolyWu/vs-basicvsrpp/issues
Author-email: HolyWu <holywu@gmail.com>
License-File: LICENSE
Keywords: BasicVSR++,PyTorch,VapourSynth
Classifier: Environment :: GPU :: NVIDIA CUDA
Classifier: License :: OSI Approved :: Apache Software License
Classifier: Operating System :: OS Independent
Classifier: Programming Language :: Python :: 3
Classifier: Topic :: Multimedia :: Video
Requires-Python: >=3.10
Requires-Dist: mmengine
Requires-Dist: numpy
Requires-Dist: requests
Requires-Dist: torch>=2.5.1
Requires-Dist: torchvision>=0.20.1
Requires-Dist: tqdm
Requires-Dist: vapoursynth>=66
